aedev/namespace_root_tpls/__init__.py
aedev/namespace_root_tpls/templates/de_otf_de_tpl_README.md
aedev/namespace_root_tpls/templates/de_tpl_dev_requirements.txt
aedev/namespace_root_tpls/templates/de_mtp_templates/de_otf_de_spt_namespace-root_de_otf_de_tpl_README.md
aedev/namespace_root_tpls/templates/de_sfp_docs/de_otf_de_tpl_index.rst
aedev/namespace_root_tpls/templates/de_sfp_docs/features_and_examples.rst
aedev_namespace_root_tpls-0.3.22.dist-info/licenses/LICENSE.md
aedev_namespace_root_tpls-0.3.22.dist-info/METADATA
aedev_namespace_root_tpls-0.3.22.dist-info/WHEEL
aedev_namespace_root_tpls-0.3.22.dist-info/top_level.txt
aedev_namespace_root_tpls-0.3.22.dist-info/RECORD
